connect_box/__init__.py
connect_box/data.py
connect_box/exceptions.py
connect_box/parsers.py
connect_box-0.3.0.dist-info/LICENSE
connect_box-0.3.0.dist-info/METADATA
connect_box-0.3.0.dist-info/WHEEL
connect_box-0.3.0.dist-info/top_level.txt
connect_box-0.3.0.dist-info/zip-safe
connect_box-0.3.0.dist-info/RECORD
